bpplang/__init__.py
bpplang/_default_hook_methods.py
bpplang/bpp_typing.py
bpplang/functions.py
bpplang/hooks.py
bpplang/parsing.py
bpplang/utils.py
bpplang-0.2.0.dist-info/LICENSE
bpplang-0.2.0.dist-info/METADATA
bpplang-0.2.0.dist-info/WHEEL
bpplang-0.2.0.dist-info/top_level.txt
bpplang-0.2.0.dist-info/RECORD
