Metadata-Version: 2.2
Name: bpplang
Version: 0.2.0
Summary: The B++ programming language, standalone.
Author-email: whirlingstars <infernity@infernity.dev>
License: MIT
Keywords: STORAGE
Classifier: Development Status :: 4 - Beta
Classifier: Intended Audience :: Developers
Classifier: License :: OSI Approved :: MIT License
Classifier: Programming Language :: Python :: 3
Classifier: Programming Language :: Python :: 3.12
Classifier: Programming Language :: Python :: 3.13
License-File: LICENSE
